Metadata-Version: 2.1
Name: td-sequential-calculator
Version: 0.1.0
Summary: A library to calculating td sequental.
Home-page: https://github.com/onuratakan/td_sequential_calculator
Author: Onur Atakan ULUSOY
Author-email: atadogan06@gmail.com
License: MIT
Platform: UNKNOWN
Requires-Python: >= 3
License-File: LICENSE
